{"cameraMode":{"drawMode":0,"name":"Shaded","section":"Shading Mode"},"sceneLighting":true,"audioPlay":false,"sceneViewState":{"showFog":true,"showMaterialUpdate":false,"showSkybox":true,"showFlares":true,"showImageEffects":true,"showParticleSystems":true},"in2DMode":false,"pivot":{"x":-22.63201332092285,"y":3.6419990062713625,"z":-179.01583862304688},"rotation":{"x":0.16350193321704865,"y":-0.44868406653404238,"z":0.08387549221515656,"w":0.8746022582054138},"size":1.3161728382110596,"orthographic":false}